infobip_channels/__init__.py
infobip_channels/core/__init__.py
infobip_channels/core/channel.py
infobip_channels/core/http_client.py
infobip_channels/core/models.py
infobip_channels/email/__init__.py
infobip_channels/email/channel.py
infobip_channels/email/models/__init__.py
infobip_channels/email/models/body/__init__.py
infobip_channels/email/models/body/add_new_domain.py
infobip_channels/email/models/body/reschedule_messages.py
infobip_channels/email/models/body/send_email.py
infobip_channels/email/models/body/update_scheduled_status.py
infobip_channels/email/models/body/update_tracking_events.py
infobip_channels/email/models/body/validate_email_addresses.py
infobip_channels/email/models/path_parameters/__init__.py
infobip_channels/email/models/path_parameters/core.py
infobip_channels/email/models/path_parameters/delete_existing_domain.py
infobip_channels/email/models/path_parameters/get_domain_details.py
infobip_channels/email/models/path_parameters/update_tracking_events.py
infobip_channels/email/models/path_parameters/verify_domain.py
infobip_channels/email/models/query_parameters/__init__.py
infobip_channels/email/models/query_parameters/core.py
infobip_channels/email/models/query_parameters/delivery_reports.py
infobip_channels/email/models/query_parameters/get_all_domains.py
infobip_channels/email/models/query_parameters/get_logs.py
infobip_channels/email/models/query_parameters/get_sent_bulks.py
infobip_channels/email/models/query_parameters/get_sent_bulks_status.py
infobip_channels/email/models/query_parameters/reschedule_messages.py
infobip_channels/email/models/query_parameters/update_scheduled_status.py
infobip_channels/email/models/response/__init__.py
infobip_channels/email/models/response/add_new_domain.py
infobip_channels/email/models/response/core.py
infobip_channels/email/models/response/delivery_reports.py
infobip_channels/email/models/response/get_all_domains.py
infobip_channels/email/models/response/get_domain_details.py
infobip_api_python_sdk-5.0.1.dist-info/LICENSE
infobip_api_python_sdk-5.0.1.dist-info/METADATA
infobip_api_python_sdk-5.0.1.dist-info/WHEEL
infobip_api_python_sdk-5.0.1.dist-info/top_level.txt
infobip_api_python_sdk-5.0.1.dist-info/RECORD
