Metadata-Version: 2.1
Name: infobip-api-python-sdk
Version: 5.0.1
Summary: Python sdk for Infobip's API
Home-page: https://github.com/infobip-community/infobip-api-python-sdk
Author: Luka Kilic, Dino Lozina, Erick Corona
Author-email: DevRel@infobip.com
Project-URL: Bug Tracker, https://github.com/infobip-community/infobip-api-python-sdk/issues
Keywords: infobip,sdk,channels,sms,whatsapp,email,webrtc,mms,api
Classifier: Programming Language :: Python :: 3
Classifier: License :: OSI Approved :: MIT License
Classifier: Operating System :: OS Independent
Requires-Python: >=3.6
License-File: LICENSE
